text/__init__.py
text/text.py
text/words.py
text_word-1.0.0.dist-info/METADATA
text_word-1.0.0.dist-info/WHEEL
text_word-1.0.0.dist-info/top_level.txt
text_word-1.0.0.dist-info/RECORD
